Workbook

Sheet F-GA-010
C1: SOLICITUD DE CONTRATACIÓN DE SERVICIOS | J1: Código | K1: F-GA-010
J2: Versión | K2: 5
C3: Gestión Administrativa | J3: Fecha | K3: 46062
A4: Fecha Solicitud | F4: Dependencia
A5: Nombre del solicitante | I5: Cargo
A7: Servicio | C7: Cantidad | D7: Centro de costos | F7: Rubro | H7: Disponibilidad presupuestal | I7: Fondo | J7: Funcion
D8: Nombre | E8: Código | F8: Nombre | G8: Código | J8: Funcion | L8: Código
D9: 1ER ENCUENTRO SOBRE EXPERIENCIAS DE INTERVENCIÓN SOCIAL EN COMUNIDADES | E9: =VLOOKUP(D9,CC!$B$1:C1719,2,) -> 926 | F9: ALQUILER DE IMPLEMENTOS CULTURALES | G9: =VLOOKUP(F9,rubro!$A$1:$B$143,2,) -> 512101 | J9: COSTOS ADMTIVOS_PROY. CARACT. DEL RIESGO EN ETV_DPTO. SUCRE 2025 | L9: =VLOOKUP(J9,funcion!$A$2:$B$853,2,FALSE) -> 7115
D10: - | E10: =VLOOKUP(D10,CC!$B$1:C1720,2,) -> - | F10: - | G10: =VLOOKUP(F10,rubro!$A$1:$B$143,2,) -> - | J10: - | L10: =VLOOKUP(J10,funcion!$A$2:$B$853,2,FALSE) -> -
D11: - | E11: =VLOOKUP(D11,CC!$B$1:C1721,2,) -> - | F11: - | G11: =VLOOKUP(F11,rubro!$A$1:$B$143,2,) -> - | J11: - | L11: =VLOOKUP(J11,funcion!$A$2:$B$853,2,FALSE) -> -
D12: - | E12: =VLOOKUP(D12,CC!$B$1:C1722,2,) -> - | F12: - | G12: =VLOOKUP(F12,rubro!$A$1:$B$143,2,) -> - | J12: - | L12: =VLOOKUP(J12,funcion!$A$2:$B$853,2,FALSE) -> -
D13: - | E13: =VLOOKUP(D13,CC!$B$1:C1723,2,) -> - | F13: - | G13: =VLOOKUP(F13,rubro!$A$1:$B$143,2,) -> - | J13: - | L13: =VLOOKUP(J13,funcion!$A$2:$B$853,2,FALSE) -> -
D14: - | E14: =VLOOKUP(D14,CC!$B$1:C1724,2,) -> - | F14: - | G14: =VLOOKUP(F14,rubro!$A$1:$B$143,2,) -> - | J14: - | L14: =VLOOKUP(J14,funcion!$A$2:$B$853,2,FALSE) -> -
D15: - | E15: =VLOOKUP(D15,CC!$B$1:C1725,2,) -> - | F15: - | G15: =VLOOKUP(F15,rubro!$A$1:$B$143,2,) -> - | J15: - | L15: =VLOOKUP(J15,funcion!$A$2:$B$853,2,FALSE) -> -
D16: - | E16: =VLOOKUP(D16,CC!$B$1:C1726,2,) -> - | F16: - | G16: =VLOOKUP(F16,rubro!$A$1:$B$143,2,) -> - | J16: - | L16: =VLOOKUP(J16,funcion!$A$2:$B$853,2,FALSE) -> -
D17: - | E17: =VLOOKUP(D17,CC!$B$1:C1727,2,) -> - | F17: - | G17: =VLOOKUP(F17,rubro!$A$1:$B$143,2,) -> - | J17: - | L17: =VLOOKUP(J17,funcion!$A$2:$B$853,2,FALSE) -> -
A19: Justificación de la solicitud
A23: “Asegúrese de usar la versión vigente actualizada, la impresión de este documento se considera copia no controlada”.

Sheet CC
B1: Centro de costo | C1: Codigo
B2: - | C2: -
B3: 1ER ENCUENTRO SOBRE EXPERIENCIAS DE INTERVENCIÓN SOCIAL EN COMUNIDADES | C3: 926
B4: 1ER SEMINARIO NACIONAL DE LAS CIENCIAS SOCIALES EN EL POSCONFLICTO | C4: 745
B5: ACT. PROYECCION CULTURAL EN ALIANZAS | C5: 75
B6: ACTIVIDADES CULTURALES Y CIVICAS | C6: 74
B7: ACTIVIDADES DE FOMENTO A LA SALUD | C7: 366
B8: ACTIVIDADES DE FOMENTO AL DESARROLLO HUMANO | C8: 81
B9: ACTIVIDADES DE FOMENTO AL MEJORAMIENTO ACADÉMICO | C9: 85
B10: ACTIVIDADES DEPORTIVAS | C10: 78
B11: ACTIVIDADES OFICINA DE PSICOLOGIA BIENESTAR UNIVERSITARIO | C11: 323
B12: ACTIVIDADES SEGUIMIENTO A GRADUADOS | C12: 322
B13: ACTIVIDADES VACACIONES RECREATIVAS | C13: 1138
B14: ACTUALIZACIÓN DE LA NORMA 3100 DE HABILITACIÓN | C14: 1234
... B1719: ZONAS DE ESPARCIMIENTO | C1719: 326

Sheet Hoja1

Sheet rubro
A1: Rubro | B1: Código
A2: - | B2: -
A3: ACTIVIDADES CULTURALES, DE BIENESTAR Y RECREACION | B3: 519514
A4: ACUEDUCTO Y ALCANTARILLADO | B4: 513504
A5: AFILIACIONES Y SOSTENIMIENTO | B5: 512501
A6: ALOJAMIENTO Y MANUTENCION | B6: 515501
A7: ALQUILER DE CONSTRUCCIONES Y EDIFICACIONES | B7: 512001
A8: ALQUILER DE EQUIPOS DE COMPUTO Y TELECOMUNICACIONES | B8: 512004
A9: ALQUILER DE EQUIPOS LEASING | B9: 512005
A10: ALQUILER DE IMPLEMENTOS CULTURALES | B10: 512101
A11: ALQUILER DE MAQUINARIA Y EQUIPO | B11: 512002
A12: ALQUILER DE MUEBLES, ENSERES Y EQUIPOS DE OFICINA | B12: 512003
A13: APORTES FONDO DE SOSTENIBILIDAD ICETEX | B13: 519611
A14: APORTES SUBFONDO ICETEX CREDITOS SIN CODEUDOR | B14: 519610
... A143: VIGILANCIA Y SEGURIDAD | B143: 513502

Sheet funcion
A1: Funcion | B1: Codigo
A2: - | B2: -
A3: % CUMPLIMIENTO DE LAS ACCIONES CORRECTIVA Y OPORTUNIDADES DE MEJORA DEL PROCESO | B3: 8013022
A4: % CUMPLIMIENTO DE LOS ESTANDARES MINIMOS DEL SG-SST RES 0312 2019 | B4: 8012060
A5: % DE PONENCIAS ESTUDIANTILES EN EVENTOS DE CARACTER NACIONAL E INTERNACIONAL | B5: 8001071
A6: % DE PORYECTOS DE INVESTIGACION CON PARTICIPACION INTERNACIONAL | B6: 8001065
A7: % DE PRODUCTOS DE DESAROOLLO TECNOLOGICO APLICADOS EN LOS SECTORES ECONOMICOS | B7: 8001070
A8: % DE PROYECTOS CON IMPACTO DIRECTO EN EL DESAROLLO SOCIAL CULTURAL COMUNITARIO E | B8: 8001072
A9: % DE PUBLICACIONES ACA INV Y DE CREACION LITERARIA DIVULGADAS A TRAVES DEL SELLO | B9: 8002010
A10: % DE PUBLICACIONES EN REVISTAS IDEXADAS (DIFERENTES A A1 A2 Q 1 Q2 | B10: 8001073
A11: % DE PUBLICACIONES EN REVISTAS INDEXADAS DE ALTO IMPACTO (A1-A2 PUBLINDEX O Q1-Q | B11: 8001061
A12: % DEL DESARROLLO DE ACCIONES PARA EL CUMPLIMIENTO RESULTADOS DE APRENDIZAJE | B12: 8018038
A13: % EJECUCION DEL PLAN DE MANTENIMIENTO Y CALIBRACION DE EQUIPOS LABORATORIO | B13: 8020011
A14: % ESTUDIANTES CON AJUSTES RAZONABLES QUE LE SON APLICABLES Y EJECUTADOS | B14: 8019016
... A853: VIAJES - REALIZACIÓN DE PONENCIA EN EVENTO CIENTÍFICO NACIONAL Y/O INT | B853: 7011
